sentiment_analysis/Logistic_model.pkl
sentiment_analysis/__init__.py
sentiment_analysis/model.py
sentiment_analysis/vectorizer.pkl
sentiment_New_package-0.1.11.dist-info/METADATA
sentiment_New_package-0.1.11.dist-info/WHEEL
sentiment_New_package-0.1.11.dist-info/top_level.txt
sentiment_New_package-0.1.11.dist-info/RECORD
